servicex/__init__.py
servicex/transformer/__init__.py
servicex/transformer/arrow_writer.py
servicex/transformer/object_store_manager.py
servicex/transformer/rabbit_mq_manager.py
servicex/transformer/scratch_file_writer.py
servicex/transformer/servicex_adapter.py
servicex/transformer/transformer_argument_parser.py
servicex/transformer/uproot_events.py
servicex/transformer/uproot_transformer.py
servicex/transformer/tests/__init__.py
servicex/transformer/tests/test_arrow_writer.py
servicex/transformer/tests/test_object_store_manager.py
servicex/transformer/tests/test_rabbit_mq_manager.py
servicex/transformer/tests/test_scratch_file_writer.py
servicex/transformer/tests/test_servicex_adapter.py
servicex/transformer/tests/test_transformer_argument_parser.py
servicex_transformer-1.0.8.dist-info/LICENSE.txt
servicex_transformer-1.0.8.dist-info/METADATA
servicex_transformer-1.0.8.dist-info/WHEEL
servicex_transformer-1.0.8.dist-info/top_level.txt
servicex_transformer-1.0.8.dist-info/RECORD
