Metadata-Version: 2.1
Name: servicex-transformer
Version: 1.0.8
Summary: ServiceX Data Transformer for HEP Data
Home-page: https://github.com/ssl-hep/ServiceX_transformer
Author: Ben Galewsky
Author-email: bengal1@illinois.edu
License: bsd 3 clause
Keywords: HEP,Data Engineering,Data Lake
Classifier: Development Status :: 3 - Alpha
Classifier: Intended Audience :: Developers
Classifier: Topic :: Software Development :: Build Tools
Classifier: License :: OSI Approved :: BSD License
Classifier: Programming Language :: Python :: 2
Classifier: Programming Language :: Python :: 2.7
Requires-Python: >=2.7
License-File: LICENSE.txt
Requires-Dist: requests (==2.28.1)
Requires-Dist: uproot (==4.3.7)
Requires-Dist: awkward (==1.10.1)
Requires-Dist: lz4
Requires-Dist: xxhash
Requires-Dist: zstandard
Requires-Dist: xrootd
Requires-Dist: pyarrow (==9.0.0)
Requires-Dist: pika (==1.1.0)
Requires-Dist: minio (==7.1.12)
Requires-Dist: retry (==0.9.2)
Provides-Extra: test
Requires-Dist: pytest (>=4.6.11) ; extra == 'test'
Requires-Dist: coverage (>=5.2) ; extra == 'test'
Requires-Dist: codecov (==2.1.8) ; extra == 'test'
Requires-Dist: pytest-mock (>=2.0.0) ; extra == 'test'
Requires-Dist: flake8 (>=3.8) ; extra == 'test'
